examples/basic.py
simpcli/__init__.py
simplifiedcli-1.1.0.dist-info/METADATA
simplifiedcli-1.1.0.dist-info/WHEEL
simplifiedcli-1.1.0.dist-info/top_level.txt
simplifiedcli-1.1.0.dist-info/RECORD
