Metadata-Version: 2.4
Name: simplifiedcli
Version: 1.1.0
Summary: A simplified command line interface.
Requires-Python: >=3.13
Provides-Extra: dev
Requires-Dist: tox>=4.33.0; extra == "dev"
Requires-Dist: pytest>=8.4.2; extra == "dev"
